{
  "id": "/myproduct/mysubsystem/elasticsearch",
  "cmd": "elasticsearch -Des.network.publish_host=${HOST} -Des.http.port=${PORT_9200} -Des.transport.tcp.port=${PORT_9300}",
  "container": {
    "type": "DOCKER",
    "docker": {
      "image": "elasticsearch:latest"
    }
  },
  "ports": [
    9200,
    9300
  ],
  "instances": 3,
  "cpus": 0.1,
  "mem": 500.0,
  "healthChecks": [
    {
      "protocol": "HTTP",
      "path": "/_cluster/health",
      "portIndex": 0,
      "gracePeriodSeconds": 15,
      "intervalSeconds": 10,
      "timeoutSeconds": 5,
      "maxConsecutiveFailures": 3
    }
  ]
}
